{"cameraMode":{"drawMode":0,"name":"Shaded","section":"Shading Mode"},"sceneLighting":true,"audioPlay":false,"sceneViewState":{"showFog":true,"showMaterialUpdate":false,"showSkybox":true,"showFlares":true,"showImageEffects":true,"showParticleSystems":true},"in2DMode":false,"pivot":{"x":-164.15536499023438,"y":-17.318279266357423,"z":12.491615295410157},"rotation":{"x":0.26556918025016787,"y":0.01042398251593113,"z":-0.0028694020584225656,"w":0.9640312194824219},"size":93.61884307861328,"orthographic":false}